VRPSolverEasy/__init__.py
VRPSolverEasy/demos/CVRP.py
VRPSolverEasy/demos/CVRPTW.py
VRPSolverEasy/demos/HFVRP.py
VRPSolverEasy/demos/MDVRP.py
VRPSolverEasy/demos/RichVRP.py
VRPSolverEasy/demos/__init__.py
VRPSolverEasy/demos/example.py
VRPSolverEasy/demos/data/CVRP/A-n32-k5.vrp
VRPSolverEasy/demos/data/CVRP/A-n33-k5.vrp
VRPSolverEasy/demos/data/CVRP/A-n33-k6.vrp
VRPSolverEasy/demos/data/CVRP/A-n34-k5.vrp
VRPSolverEasy/demos/data/CVRP/A-n36-k5.vrp
VRPSolverEasy/demos/data/CVRP/A-n37-k5.vrp
VRPSolverEasy/demos/data/CVRP/A-n37-k6.vrp
VRPSolverEasy/demos/data/CVRP/A-n38-k5.vrp
VRPSolverEasy/demos/data/CVRP/A-n39-k5.vrp
VRPSolverEasy/demos/data/CVRP/A-n39-k6.vrp
VRPSolverEasy/demos/data/CVRP/A-n44-k6.vrp
VRPSolverEasy/demos/data/CVRP/A-n45-k6.vrp
VRPSolverEasy/demos/data/CVRP/A-n45-k7.vrp
VRPSolverEasy/demos/data/CVRP/A-n46-k7.vrp
VRPSolverEasy/demos/data/CVRP/A-n48-k7.vrp
VRPSolverEasy/demos/data/CVRP/A-n53-k7.vrp
VRPSolverEasy/demos/data/CVRP/A-n54-k7.vrp
VRPSolverEasy/demos/data/CVRP/A-n55-k9.vrp
VRPSolverEasy/demos/data/CVRP/A-n60-k9.vrp
VRPSolverEasy/demos/data/CVRP/A-n61-k9.vrp
VRPSolverEasy/demos/data/CVRP/A-n62-k8.vrp
VRPSolverEasy/demos/data/CVRP/A-n63-k10.vrp
VRPSolverEasy/demos/data/CVRP/A-n63-k9.vrp
VRPSolverEasy/demos/data/CVRP/A-n64-k9.vrp
VRPSolverEasy/demos/data/CVRP/A-n65-k9.vrp
VRPSolverEasy/demos/data/CVRP/A-n69-k9.vrp
VRPSolverEasy/demos/data/CVRP/A-n80-k10.vrp
VRPSolverEasy/demos/data/CVRP/B-n31-k5.vrp
VRPSolverEasy/demos/data/CVRP/B-n34-k5.vrp
VRPSolverEasy/demos/data/CVRP/B-n35-k5.vrp
VRPSolverEasy/demos/data/CVRP/B-n38-k6.vrp
VRPSolverEasy/demos/data/CVRP/B-n39-k5.vrp
VRPSolverEasy/demos/data/CVRP/B-n41-k6.vrp
VRPSolverEasy/demos/data/CVRP/B-n43-k6.vrp
VRPSolverEasy/demos/data/CVRP/B-n44-k7.vrp
VRPSolverEasy/demos/data/CVRP/B-n45-k5.vrp
VRPSolverEasy/demos/data/CVRP/B-n45-k6.vrp
VRPSolverEasy/demos/data/CVRP/B-n50-k7.vrp
VRPSolverEasy/demos/data/CVRP/B-n50-k8.vrp
VRPSolverEasy/demos/data/CVRP/B-n51-k7.vrp
VRPSolverEasy-0.1.4.dist-info/LICENSE.txt
VRPSolverEasy-0.1.4.dist-info/METADATA
VRPSolverEasy-0.1.4.dist-info/WHEEL
VRPSolverEasy-0.1.4.dist-info/entry_points.txt
VRPSolverEasy-0.1.4.dist-info/top_level.txt
VRPSolverEasy-0.1.4.dist-info/RECORD
