Metadata-Version: 2.1
Name: VRPSolverEasy
Version: 0.1.4
Summary: 'VRPSolverEasy is a simplified modeler solving routing problems by using a Branch-Cut-and-Price approach on a solver like CLP or CPLEX'
Home-page: https://github.com/inria-UFF/VRPSolverEasy
Author: "UCHOA Eduardo SADYKOV Ruslan QUEIROGA Eduardo ERRAMI Najib"
Author-email: "najib.errami@inria.fr"
Keywords: ['VRP','Branch-Cut-&Price','Operations Research','Optimization','Linear Programming','Routing problems','Solver','Supply chain']
Classifier: Development Status :: 4 - Beta
Classifier: Environment :: Console
Classifier: Intended Audience :: Science/Research
Classifier: Topic :: Scientific/Engineering :: Mathematics
Classifier: License :: OSI Approved :: MIT License
Classifier: Operating System :: MacOS
Classifier: Operating System :: Microsoft :: Windows
Classifier: Operating System :: POSIX :: Linux
Classifier: Programming Language :: Python :: 3
Classifier: Natural Language :: English
Requires-Python: >=3.6
License-File: LICENSE.txt
